sentencesimilarity/__init__.py
sentencesimilarity/sentences_similarity.py
tests/__init__.py
tests/test_sentences_similarity.py
sentencesimilarity-0.1.1.dist-info/LICENSE.txt
sentencesimilarity-0.1.1.dist-info/METADATA
sentencesimilarity-0.1.1.dist-info/WHEEL
sentencesimilarity-0.1.1.dist-info/top_level.txt
sentencesimilarity-0.1.1.dist-info/RECORD
