Metadata-Version: 2.1
Name: sentencesimilarity
Version: 0.1.1
Summary: Calculates semantic similarity between given sentences.
Home-page: UNKNOWN
Author: osahin
Author-email: oguuzhansahiin@gmail.com
License: MIT
Platform: UNKNOWN
Requires-Dist: scikit-learn (==0.24.2)
Requires-Dist: torch (==1.9.0)
Requires-Dist: transformers (==4.9.2)
